debus/__init__.py
debus/buses.py
debus/connection.py
debus/message.py
debus/objects.py
debus/pybus_struct.cpython-36m-darwin.so
debus/subscription.py
debus/types.py
debus/wire.py
debus/freedesktop/__init__.py
debus/freedesktop/introspect.py
debus/freedesktop/properties.py
debus-0.1.dist-info/DESCRIPTION.rst
debus-0.1.dist-info/METADATA
debus-0.1.dist-info/RECORD
debus-0.1.dist-info/WHEEL
debus-0.1.dist-info/metadata.json
debus-0.1.dist-info/top_level.txt
